[
  {
    "name": "AnimeGG",
    "id": 209614032,
    "baseUrl": "https://www.animegg.org",
    "lang": "en",
    "typeSource": "single",
    "iconUrl": "https://raw.githubusercontent.com/RyanYuuki/AnymeX/main/assets/images/logo.png",
    "dateFormat": "",
    "dateFormatLocale": "",
    "isNsfw": false,
    "hasCloudflare": false,
    "sourceCodeUrl": "https://anymex.vercel.app/extensions/anime/src/en/animegg.js",
    "apiUrl": "",
    "version": "1.0.3",
    "isManga": false,
    "itemType": 1,
    "isFullData": false,
    "appMinVerReq": "0.5.0",
    "additionalParams": "",
    "sourceCodeLanguage": 1,
    "notes": ""
  },
  {
    "name": "AnimeZZ",
    "id": 492689523,
    "baseUrl": "https://animeyy.com",
    "lang": "en",
    "typeSource": "multi",
    "iconUrl": "https://raw.githubusercontent.com/RyanYuuki/AnymeX/main/assets/images/logo.png",
    "dateFormat": "",
    "dateFormatLocale": "",
    "isNsfw": false,
    "hasCloudflare": false,
    "sourceCodeUrl": "https://anymex.vercel.app/extensions/anime/src/en/animezz.js",
    "apiUrl": "",
    "version": "1.1.1",
    "isManga": false,
    "itemType": 1,
    "isFullData": false,
    "appMinVerReq": "0.5.0",
    "additionalParams": "",
    "sourceCodeLanguage": 1,
    "notes": ""
  },
  {
    "name": "Aniwatch",
    "id": 1514967419,
    "baseUrl": "https://aniwatchtv.to",
    "lang": "en",
    "typeSource": "single",
    "iconUrl": "https://raw.githubusercontent.com/RyanYuuki/AnymeX/main/assets/images/logo.png",
    "dateFormat": "",
    "dateFormatLocale": "",
    "isNsfw": false,
    "hasCloudflare": false,
    "sourceCodeUrl": "https://anymex.vercel.app/extensions/anime/src/en/aniwatch.js",
    "apiUrl": "",
    "version": "1.0.0",
    "isManga": false,
    "itemType": 1,
    "isFullData": false,
    "appMinVerReq": "0.5.0",
    "additionalParams": "",
    "sourceCodeLanguage": 1,
    "notes": ""
  },
  {
    "name": "Sudatchi",
    "id": 398530136,
    "baseUrl": "https://sudatchi.com",
    "lang": "en",
    "typeSource": "single",
    "iconUrl": "https://raw.githubusercontent.com/RyanYuuki/AnymeX/main/assets/images/logo.png",
    "dateFormat": "",
    "dateFormatLocale": "",
    "isNsfw": false,
    "hasCloudflare": false,
    "sourceCodeUrl": "https://anymex.vercel.app/extensions/anime/src/en/sudatchi.js",
    "apiUrl": "",
    "version": "1.1.1",
    "isManga": false,
    "itemType": 1,
    "isFullData": false,
    "appMinVerReq": "0.5.0",
    "additionalParams": "",
    "sourceCodeLanguage": 1,
    "notes": ""
  },
  {
    "name": "Anixl",
    "id": 2448777672,
    "baseUrl": "https://anixl.to",
    "lang": "en",
    "typeSource": "multi",
    "iconUrl": "https://raw.githubusercontent.com/RyanYuuki/AnymeX/main/assets/images/logo.png",
    "dateFormat": "",
    "dateFormatLocale": "",
    "isNsfw": false,
    "hasCloudflare": false,
    "sourceCodeUrl": "https://anymex.vercel.app/extensions/anime/src/en/anixl.js",
    "apiUrl": "",
    "version": "0.0.81",
    "isManga": false,
    "itemType": 1,
    "isFullData": false,
    "appMinVerReq": "0.5.0",
    "additionalParams": "",
    "sourceCodeLanguage": 1,
    "notes": ""
  },
  {
    "name": "Anicrush",
    "id": 1497004903,
    "baseUrl": "https://anicrush.to",
    "lang": "en",
    "typeSource": "single",
    "iconUrl": "https://raw.githubusercontent.com/RyanYuuki/AnymeX/main/assets/images/logo.png",
    "dateFormat": "",
    "dateFormatLocale": "",
    "isNsfw": false,
    "hasCloudflare": true,
    "sourceCodeUrl": "https://anymex.vercel.app/extensions/anime/src/en/anicrush.js",
    "apiUrl": "https://api.anicrush.to",
    "version": "0.0.5",
    "isManga": false,
    "itemType": 1,
    "isFullData": false,
    "appMinVerReq": "0.5.0",
    "additionalParams": "",
    "sourceCodeLanguage": 1,
    "notes": ""
  },
  {
    "name": "Animeonsen",
    "id": 1004796349,
    "baseUrl": "https://www.animeonsen.xyz",
    "lang": "en",
    "typeSource": "single",
    "iconUrl": "https://raw.githubusercontent.com/RyanYuuki/AnymeX/main/assets/images/logo.png",
    "dateFormat": "",
    "dateFormatLocale": "",
    "isNsfw": false,
    "hasCloudflare": false,
    "sourceCodeUrl": "https://anymex.vercel.app/extensions/anime/src/all/animeonsen.js",
    "apiUrl": "https://api.animeonsen.xyz",
    "version": "1.0.1",
    "isManga": false,
    "itemType": 1,
    "isFullData": false,
    "appMinVerReq": "0.5.0",
    "additionalParams": "",
    "sourceCodeLanguage": 1,
    "notes": ""
  },
  {
    "name": "Animeonsen",
    "id": 1004796349,
    "baseUrl": "https://www.animeonsen.xyz",
    "lang": "ja",
    "typeSource": "single",
    "iconUrl": "https://raw.githubusercontent.com/RyanYuuki/AnymeX/main/assets/images/logo.png",
    "dateFormat": "",
    "dateFormatLocale": "",
    "isNsfw": false,
    "hasCloudflare": false,
    "sourceCodeUrl": "https://anymex.vercel.app/extensions/anime/src/all/animeonsen.js",
    "apiUrl": "https://api.animeonsen.xyz",
    "version": "1.0.1",
    "isManga": false,
    "itemType": 1,
    "isFullData": false,
    "appMinVerReq": "0.5.0",
    "additionalParams": "",
    "sourceCodeLanguage": 1,
    "notes": ""
  },
  {
    "name": "AnimeParadise",
    "id": 419768715,
    "baseUrl": "https://animeparadise.moe",
    "lang": "en",
    "typeSource": "single",
    "iconUrl": "https://raw.githubusercontent.com/RyanYuuki/AnymeX/main/assets/images/logo.png",
    "dateFormat": "",
    "dateFormatLocale": "",
    "isNsfw": false,
    "hasCloudflare": false,
    "sourceCodeUrl": "https://anymex.vercel.app/extensions/anime/src/en/animeparadise.js",
    "apiUrl": "https://api.animeparadise.moe",
    "version": "0.1.0",
    "isManga": false,
    "itemType": 1,
    "isFullData": false,
    "appMinVerReq": "0.5.0",
    "additionalParams": "",
    "sourceCodeLanguage": 1,
    "notes": ""
  },
  {
    "name": "Gojo",
    "id": 1018827104,
    "baseUrl": "https://gojo.wtf",
    "lang": "en",
    "typeSource": "multi",
    "iconUrl": "https://raw.githubusercontent.com/RyanYuuki/AnymeX/main/assets/images/logo.png",
    "dateFormat": "",
    "dateFormatLocale": "",
    "isNsfw": false,
    "hasCloudflare": false,
    "sourceCodeUrl": "https://anymex.vercel.app/extensions/anime/src/en/gojo.js",
    "apiUrl": "",
    "version": "0.0.6",
    "isManga": false,
    "itemType": 1,
    "isFullData": false,
    "appMinVerReq": "0.5.0",
    "additionalParams": "",
    "sourceCodeLanguage": 1,
    "notes": ""
  },
  {
    "name": "SubsPlease",
    "id": 2732508901,
    "baseUrl": "https://subsplease.org",
    "lang": "en",
    "typeSource": "single",
    "iconUrl": "https://raw.githubusercontent.com/RyanYuuki/AnymeX/main/assets/images/logo.png",
    "dateFormat": "",
    "dateFormatLocale": "",
    "isNsfw": false,
    "hasCloudflare": false,
    "sourceCodeUrl": "https://anymex.vercel.app/extensions/anime/src/en/subsplease.js",
    "apiUrl": "https://subsplease.org/api",
    "version": "0.0.5",
    "isManga": false,
    "itemType": 1,
    "isFullData": false,
    "appMinVerReq": "0.5.0",
    "additionalParams": "",
    "sourceCodeLanguage": 1,
    "notes": ""
  },
  {
    "name": "Kaido",
    "id": 2457624982,
    "baseUrl": "https://kaido.to",
    "lang": "en",
    "typeSource": "single",
    "iconUrl": "https://raw.githubusercontent.com/RyanYuuki/AnymeX/main/assets/images/logo.png",
    "dateFormat": "",
    "dateFormatLocale": "",
    "isNsfw": false,
    "hasCloudflare": false,
    "sourceCodeUrl": "https://anymex.vercel.app/extensions/anime/src/en/kaido.js",
    "apiUrl": "",
    "version": "1.0.2",
    "isManga": false,
    "itemType": 1,
    "isFullData": false,
    "appMinVerReq": "0.5.0",
    "additionalParams": "",
    "sourceCodeLanguage": 1,
    "notes": ""
  },
  {
    "name": "KickAssAnime",
    "id": 4096048097,
    "baseUrl": "https://kaa.to",
    "lang": "en",
    "typeSource": "multi",
    "iconUrl": "https://raw.githubusercontent.com/RyanYuuki/AnymeX/main/assets/images/logo.png",
    "dateFormat": "",
    "dateFormatLocale": "",
    "isNsfw": false,
    "hasCloudflare": false,
    "sourceCodeUrl": "https://anymex.vercel.app/extensions/anime/src/en/kickassanime.js",
    "apiUrl": "",
    "version": "1.2.5",
    "isManga": false,
    "itemType": 1,
    "isFullData": false,
    "appMinVerReq": "0.5.0",
    "additionalParams": "",
    "sourceCodeLanguage": 1,
    "notes": ""
  },
  {
    "name": "Aniwave",
    "id": 3928195277,
    "baseUrl": "https://aniwave.se",
    "lang": "en",
    "typeSource": "multi",
    "iconUrl": "https://raw.githubusercontent.com/RyanYuuki/AnymeX/main/assets/images/logo.png",
    "dateFormat": "",
    "dateFormatLocale": "",
    "isNsfw": false,
    "hasCloudflare": false,
    "sourceCodeUrl": "https://anymex.vercel.app/extensions/anime/src/en/aniwave.js",
    "apiUrl": "",
    "version": "1.0.0",
    "isManga": false,
    "itemType": 1,
    "isFullData": false,
    "appMinVerReq": "0.5.0",
    "additionalParams": "",
    "sourceCodeLanguage": 1,
    "notes": ""
  }
]
